astrohack/__init__.py
astrohack/beamcut.py
astrohack/cassegrain_ray_tracing.py
astrohack/combine.py
astrohack/extract_holog.py
astrohack/extract_locit.py
astrohack/extract_pointing.py
astrohack/holog.py
astrohack/image_comparison_tool.py
astrohack/locit.py
astrohack/panel.py
astrohack/antenna/__init__.py
astrohack/antenna/antenna_surface.py
astrohack/antenna/base_panel.py
astrohack/antenna/panel_fitting.py
astrohack/antenna/polygon_panel.py
astrohack/antenna/ring_panel.py
astrohack/antenna/telescope.py
astrohack/config/beamcut.param.json
astrohack/config/beamcut_mds.param.json
astrohack/config/cassegrain_ray_tracing.param.json
astrohack/config/combine.param.json
astrohack/config/create_param_json.py
astrohack/config/dask.config.yaml
astrohack/config/extract_holog.param.json
astrohack/config/extract_locit.param.json
astrohack/config/extract_pointing.param.json
astrohack/config/holog.param.json
astrohack/config/image_comparison_tool.param.json
astrohack/config/locit.param.json
astrohack/config/mds.param.json
astrohack/config/panel.param.json
astrohack/core/__init__.py
astrohack/core/beamcut.py
astrohack/core/cassegrain_ray_tracing.py
astrohack/core/combine.py
astrohack/core/extract_holog.py
astrohack/core/extract_locit.py
astrohack/core/extract_pointing.py
astrohack/core/holog.py
astrohack/core/image_comparison_tool.py
astrohack/core/locit.py
astrohack/core/panel.py
astrohack/data/telescopes/fix_telescope_files.bash
astrohack/data/telescopes/aca_7m.zarr/.zattrs
astrohack/data/telescopes/aca_7m.zarr/.zgroup
astrohack/data/telescopes/aca_7m.zarr/.zmetadata
astrohack/data/telescopes/alma_da.zarr/.zattrs
astrohack/data/telescopes/alma_da.zarr/.zgroup
astrohack/data/telescopes/alma_da.zarr/.zmetadata
astrohack/data/telescopes/alma_dv.zarr/.zattrs
astrohack/data/telescopes/alma_dv.zarr/.zgroup
astrohack/data/telescopes/alma_dv.zarr/.zmetadata
astrohack/data/telescopes/alma_tp.zarr/.zattrs
astrohack/data/telescopes/alma_tp.zarr/.zgroup
astrohack-0.10.1.dist-info/licenses/LICENSE
astrohack-0.10.1.dist-info/METADATA
astrohack-0.10.1.dist-info/WHEEL
astrohack-0.10.1.dist-info/top_level.txt
astrohack-0.10.1.dist-info/RECORD
