Metadata-Version: 2.4
Name: astrohack
Version: 0.10.1
Summary: Holography Antenna Commissioning Kit
Author-email: Joshua Hoskins <jhoskins@nrao.edu>, Victor de Souza Magalhaes <vdesouza@nrao.edu>, Jan-Willem Steeb <jsteeb@nrao.edu>
Requires-Python: <3.14,>=3.11
License-File: LICENSE
Requires-Dist: astropy
Requires-Dist: dask
Requires-Dist: shapely
Requires-Dist: distributed
Requires-Dist: dropbox
Requires-Dist: toolviper
Requires-Dist: ipywidgets
Requires-Dist: matplotlib
Requires-Dist: numba>=0.57.0
Requires-Dist: numpy<=2.2
Requires-Dist: prettytable
Requires-Dist: pycryptodome
Requires-Dist: pytest
Requires-Dist: pytest-cov
Requires-Dist: pytest-html
Requires-Dist: scikit_image
Requires-Dist: scikit-learn
Requires-Dist: scipy
Requires-Dist: rich
Requires-Dist: xarray
Requires-Dist: zarr<3.0.0
Requires-Dist: bokeh
Requires-Dist: pillow
Requires-Dist: jupyterlab
Requires-Dist: python_casacore>=3.6.1; sys_platform != "darwin"
Provides-Extra: docs
Requires-Dist: ipykernel; extra == "docs"
Requires-Dist: ipympl; extra == "docs"
Requires-Dist: ipython; extra == "docs"
Requires-Dist: jupyter-client; extra == "docs"
Requires-Dist: nbsphinx; extra == "docs"
Requires-Dist: recommonmark; extra == "docs"
Requires-Dist: scanpydoc; extra == "docs"
Requires-Dist: sphinx-autoapi; extra == "docs"
Requires-Dist: sphinx-autosummary-accessors; extra == "docs"
Requires-Dist: sphinx_rtd_theme; extra == "docs"
Requires-Dist: twine; extra == "docs"
Requires-Dist: pandoc; extra == "docs"
Dynamic: license-file
